logtop/__init__.py
logtop/logtop.py
logtop-0.0.1.dist-info/LICENCE
logtop-0.0.1.dist-info/METADATA
logtop-0.0.1.dist-info/WHEEL
logtop-0.0.1.dist-info/top_level.txt
logtop-0.0.1.dist-info/RECORD
