Metadata-Version: 2.1
Name: logtop
Version: 0.0.1
Summary: Package for easy loging
Home-page: https://github.com/RmValn/logtop
Author: Valentyn Romaniuk
Author-email: valik8355@gmail.com
License: UNKNOWN
Project-URL: Bug Tracker, https://github.com/RmValn/logtop/issues
Platform: UNKNOWN
Classifier: Programming Language :: Python :: 3
Classifier: License :: OSI Approved :: MIT License
Classifier: Operating System :: OS Independent
Requires-Python: >=3.6
License-File: LICENCE
Requires-Dist: loguru
